django_gar/__init__.py
django_gar/admin.py
django_gar/apps.py
django_gar/backends.py
django_gar/exceptions.py
django_gar/forms.py
django_gar/gar.py
django_gar/middleware.py
django_gar/models.py
django_gar/urls.py
django_gar/views.py
django_gar/management/__init__.py
django_gar/management/commands/__init__.py
django_gar/management/commands/refresh_gar_caches.py
django_gar/management/commands/refresh_gar_idents.py
django_gar/migrations/0001_initial.py
django_gar/migrations/0002_garinstitution_subscription_id.py
django_gar/migrations/0003_auto_20201001_1054.py
django_gar/migrations/0004_garsession.py
django_gar/migrations/0005_garinstitution_project_code.py
django_gar/migrations/0006_garinstitution_id_ent.py
django_gar/migrations/0007_garinstitution_allocations_cache_and_more.py
django_gar/migrations/0008_garinstitution_subscription_cache_and_more.py
django_gar/migrations/__init__.py
django_gar/signals/__init__.py
django_gar/signals/handlers.py
django_gar/templates/admin/django_gar/change_list.html
django_gar/templates/django_gar/logout.html
django_gar-4.1.0.dist-info/LICENSE
django_gar-4.1.0.dist-info/METADATA
django_gar-4.1.0.dist-info/WHEEL
django_gar-4.1.0.dist-info/top_level.txt
django_gar-4.1.0.dist-info/RECORD
