Metadata-Version: 2.1
Name: django-gar
Version: 4.1.0
Summary: Handle login and ticket validation for french GAR
Home-page: https://github.com/briefmnews/django-gar
Author: Brief.me
Author-email: tech@brief.me
License: GNU GPL v3
Classifier: Environment :: Web Environment
Classifier: Framework :: Django
Classifier: Framework :: Django :: 4.2
Classifier: Operating System :: OS Independent
Classifier: Programming Language :: Python
Classifier: Topic :: Software Development :: Libraries :: Python Modules
Classifier: Programming Language :: Python
Classifier: Programming Language :: Python :: 3
Classifier: Programming Language :: Python :: 3.9
Classifier: Programming Language :: Python :: 3.10
Classifier: Programming Language :: Python :: 3.11
Classifier: Programming Language :: Python :: 3.12
Classifier: Programming Language :: Python :: 3.13
Requires-Python: >=3.9
License-File: LICENSE
Requires-Dist: Django>=4.2
Requires-Dist: python-cas>=1.6.0
Requires-Dist: lxml>=4.9.4
Requires-Dist: defusedxml>=0.7.1
Requires-Dist: requests>=2.29.0
